endpointsorter/__init__.py
endpointsorter/endpointsorter.py
urlsorter/__init__.py
urlsorter/urlsorter.py
endpointsorter-1.1.3.dist-info/METADATA
endpointsorter-1.1.3.dist-info/WHEEL
endpointsorter-1.1.3.dist-info/entry_points.txt
endpointsorter-1.1.3.dist-info/top_level.txt
endpointsorter-1.1.3.dist-info/RECORD
