Metadata-Version: 2.1
Name: endpointsorter
Version: 1.1.3
Summary: A sorter tool for endpoints
Author: Praveen
Author-email: mspraveenkumar77@gmail.com
